[
    {
        "place_id": 198134367,
        "licence": "Data © OpenStreetMap contributors, ODbL 1.0. https://osm.org/copyright",
        "osm_type": "relation",
        "osm_id": 112224,
        "boundingbox": [
            "34.336029",
            "34.463922",
            "-119.859791",
            "-119.639946"
        ],
        "lat": "34.4221319",
        "lon": "-119.7026673",
        "display_name": "Santa Barbara, Santa Barbara County, California, United States",
        "class": "place",
        "type": "city",
        "importance": 0.7840479382888761,
        "icon": "https://nominatim.openstreetmap.org/images/mapicons/poi_place_city.p.20.png"
    },
    {
        "place_id": 198096124,
        "licence": "Data © OpenStreetMap contributors, ODbL 1.0. https://osm.org/copyright",
        "osm_type": "relation",
        "osm_id": 396510,
        "boundingbox": [
            "33.4083677",
            "35.114665",
            "-120.734382",
            "-118.9633999"
        ],
        "lat": "34.7136533",
        "lon": "-119.9858232",
        "display_name": "Santa Barbara County, California, United States",
        "class": "boundary",
        "type": "administrative",
        "importance": 0.7546072318185599,
        "icon": "https://nominatim.openstreetmap.org/images/mapicons/poi_boundary_administrative.p.20.png"
    },
    {
        "place_id": 198409263,
        "licence": "Data © OpenStreetMap contributors, ODbL 1.0. https://osm.org/copyright",
        "osm_type": "relation",
        "osm_id": 315081,
        "boundingbox": [
            "-20.218",
            "-19.889",
            "-43.696",
            "-43.209"
        ],
        "lat": "-19.959444",
        "lon": "-43.415278",
        "display_name": "Santa Bárbara, Microrregião Itabira, Mesorregião Metropolitana de Belo Horizonte, Minas Gerais, Southeast Region, Brazil",
        "class": "boundary",
        "type": "administrative",
        "importance": 0.605606179366181,
        "icon": "https://nominatim.openstreetmap.org/images/mapicons/poi_boundary_administrative.p.20.png"
    },
    {
        "place_id": 198048004,
        "licence": "Data © OpenStreetMap contributors, ODbL 1.0. https://osm.org/copyright",
        "osm_type": "relation",
        "osm_id": 362549,
        "boundingbox": [
            "-12.063",
            "-11.806",
            "-39.076",
            "-38.897"
        ],
        "lat": "-11.9543757",
        "lon": "-38.9736385",
        "display_name": "Santa Bárbara, Microrregião de Feira de Santana, Região Metropolitana de Feira de Santana, Mesorregião do Centro-Norte baiano, Bahia, Northeast Region, Brazil",
        "class": "boundary",
        "type": "administrative",
        "importance": 0.555322246270835,
        "icon": "https://nominatim.openstreetmap.org/images/mapicons/poi_boundary_administrative.p.20.png"
    },
    {
        "place_id": 198106447,
        "licence": "Data © OpenStreetMap contributors, ODbL 1.0. https://osm.org/copyright",
        "osm_type": "relation",
        "osm_id": 1307234,
        "boundingbox": [
            "5.7229867",
            "6.0215927",
            "-75.6504107",
            "-75.5328605"
        ],
        "lat": "5.87213125",
        "lon": "-75.5777766103402",
        "display_name": "Santa Bárbara, Suroeste, Antioquia Department, Colombia",
        "class": "boundary",
        "type": "administrative",
        "importance": 0.55,
        "icon": "https://nominatim.openstreetmap.org/images/mapicons/poi_boundary_administrative.p.20.png"
    },
    {
        "place_id": 199345766,
        "licence": "Data © OpenStreetMap contributors, ODbL 1.0. https://osm.org/copyright",
        "osm_type": "relation",
        "osm_id": 4627395,
        "boundingbox": [
            "14.6426721",
            "15.5472873",
            "-88.7592934",
            "-87.9771042"
        ],
        "lat": "15.0944971",
        "lon": "-88.3723217829678",
        "display_name": "Santa Bárbara, Honduras",
        "class": "boundary",
        "type": "administrative",
        "importance": 0.536046957362672,
        "icon": "https://nominatim.openstreetmap.org/images/mapicons/poi_boundary_administrative.p.20.png"
    },
    {
        "place_id": 184478708,
        "licence": "Data © OpenStreetMap contributors, ODbL 1.0. https://osm.org/copyright",
        "osm_type": "way",
        "osm_id": 516405912,
        "boundingbox": [
            "42.8229493",
            "42.8286515",
            "-2.3702731",
            "-2.3666005"
        ],
        "lat": "42.8268225",
        "lon": "-2.3675025",
        "display_name": "Santa Barbara, Agurain/Salvatierra, Arabako lautada/Llanada Alavesa, Álava, Basque Country, 01207, Spain",
        "class": "waterway",
        "type": "stream",
        "importance": 0.525
    },
    {
        "place_id": 186194797,
        "licence": "Data © OpenStreetMap contributors, ODbL 1.0. https://osm.org/copyright",
        "osm_type": "way",
        "osm_id": 516368775,
        "boundingbox": [
            "42.8474827",
            "42.8475616",
            "-2.3854288",
            "-2.3853151"
        ],
        "lat": "42.8475616",
        "lon": "-2.3854288",
        "display_name": "Santa Barbara, Agurain/Salvatierra, Arabako lautada/Llanada Alavesa, Álava, Basque Country, 01200, Spain",
        "class": "waterway",
        "type": "stream",
        "importance": 0.525
    },
    {
        "place_id": 199351520,
        "licence": "Data © OpenStreetMap contributors, ODbL 1.0. https://osm.org/copyright",
        "osm_type": "relation",
        "osm_id": 5668081,
        "boundingbox": [
            "10.0056952",
            "10.1584704",
            "-84.1735498",
            "-84.1209884"
        ],
        "lat": "10.0824578",
        "lon": "-84.1462968555599",
        "display_name": "Cantón Santa Bárbara, Heredia Province, Costa Rica",
        "class": "boundary",
        "type": "administrative",
        "importance": 0.48555688494777904,
        "icon": "https://nominatim.openstreetmap.org/images/mapicons/poi_boundary_administrative.p.20.png"
    },
    {
        "place_id": 198656652,
        "licence": "Data © OpenStreetMap contributors, ODbL 1.0. https://osm.org/copyright",
        "osm_type": "relation",
        "osm_id": 3726378,
        "boundingbox": [
            "0.5442677",
            "0.6620911",
            "-77.6009043",
            "-77.478057"
        ],
        "lat": "0.60369345",
        "lon": "-77.5194447232037",
        "display_name": "Santa Bárbara, Sucumbíos, Sucumbíos Province, Ecuador",
        "class": "boundary",
        "type": "administrative",
        "importance": 0.44999999999999996,
        "icon": "https://nominatim.openstreetmap.org/images/mapicons/poi_boundary_administrative.p.20.png"
    }
]